Metadata-Version: 1.0
Name: givemestuff
Version: 0.4.1
Summary: Giveme info
Home-page: UNKNOWN
Author: Zhe Wang
Author-email: wangzhetju@gmail.com
License: UNKNOWN
Platform: UNKNOWN
